kivy_webview/__init__.py
kivy_webview/main.py
kivy_webview-0.0.0.dist-info/METADATA
kivy_webview-0.0.0.dist-info/WHEEL
kivy_webview-0.0.0.dist-info/top_level.txt
kivy_webview-0.0.0.dist-info/RECORD
